yaunqi_plugin_mcp/__init__.py
yaunqi_plugin_mcp/__main__.py
yaunqi_plugin_mcp/server.py
hunyuan_image_mcp_standard-0.1.1.dist-info/METADATA
hunyuan_image_mcp_standard-0.1.1.dist-info/WHEEL
hunyuan_image_mcp_standard-0.1.1.dist-info/entry_points.txt
hunyuan_image_mcp_standard-0.1.1.dist-info/RECORD
