Metadata-Version: 2.4
Name: hunyuan-image-mcp-standard
Version: 0.1.1
Summary: mcp server to invoke hunyuan image
Author-email: YuanqiMcp <yuanqi_mcp@tencent.com>
Keywords: hunyuan,image,mcp
Classifier: Development Status :: 4 - Beta
Classifier: Intended Audience :: Developers
Classifier: License :: OSI Approved :: MIT License
Classifier: Programming Language :: Python :: 3
Classifier: Programming Language :: Python :: 3.10
Classifier: Programming Language :: Python :: 3.11
Classifier: Programming Language :: Python :: 3.12
Classifier: Programming Language :: Python :: 3.13
Requires-Python: >=3.10
Requires-Dist: httpx>=0.28.1
Requires-Dist: mcp>=1.7.1
